prism_pull/__init__.py
prism_pull/prism_session.py
prism_pull-1.0.1.dist-info/licenses/LICENSE
prism_pull-1.0.1.dist-info/METADATA
prism_pull-1.0.1.dist-info/WHEEL
prism_pull-1.0.1.dist-info/top_level.txt
prism_pull-1.0.1.dist-info/RECORD
