Metadata-Version: 2.4
Name: prism-pull
Version: 1.0.1
Summary: Python package to pull PRISM weather data via web automation.
Author: John Baird
Project-URL: Source, https://github.com/jtbaird/prism-pull
Requires-Python: >=3.10
License-File: LICENSE
Requires-Dist: selenium
Requires-Dist: webdriver_manager
Dynamic: license-file
